LICENSE
README.md
setup.py
algo_fun/__init__.py
algo_fun/is_palindrome.py
algo_fun_palindrome.egg-info/PKG-INFO
algo_fun_palindrome.egg-info/SOURCES.txt
algo_fun_palindrome.egg-info/dependency_links.txt
algo_fun_palindrome.egg-info/top_level.txt
tests/__init__.py
tests/test_is_palindrome.py