Metadata-Version: 2.1
Name: algo-fun-palindrome
Version: 0.2.0
Summary: Project description
Home-page: https://gitlab.com/ChristopheLagaillarde/algo_fun_palindrome
Author: Christophe Lagaillarde
Author-email: chrislag94@gmail.com
License: MIT
License-File: LICENSE
